jsom/__init__.py
jsom/jsomwarnings.py
jsom/parser.py
jsom/transformer_methods.py
jsom/tests/__init__.py
jsom/tests/test_json.py
jsom/tests/test_warnings.py
jsom-0.0.5.dist-info/METADATA
jsom-0.0.5.dist-info/RECORD
jsom-0.0.5.dist-info/WHEEL
jsom-0.0.5.dist-info/top_level.txt
