Metadata-Version: 2.1
Name: jsom
Version: 0.0.5
Summary: A fast, simple parser for terribly broken JSON
Home-page: https://github.com/slavfox/jsom
Author: Slavfox
Author-email: slavfoxman@gmail.com
License: WTFPL
Keywords: dirty broken json jsom
Platform: UNKNOWN
Classifier: Development Status :: 3 - Alpha
Classifier: Programming Language :: Python :: 3.7
Classifier: Programming Language :: Python :: 3.8
Classifier: License :: Public Domain
Classifier: Operating System :: OS Independent
Classifier: Intended Audience :: Developers
Classifier: Topic :: Software Development :: Libraries :: Python Modules
Requires-Dist: lark-parser
